MANIFEST.in
README.rst
setup.py
docs/HISTORY.txt
docs/INSTALL.txt
docs/LICENSE.GPL
docs/LICENSE.txt
docs/screenshot_custom.png
docs/screenshot_filter.png
docs/screenshot_flyout_breadcrumbs.png
docs/screenshot_flyout_navigation.png
docs/screenshot_menzingen.png
docs/screenshot_onegov.png
docs/screenshot_zg_ch.png
plonetheme/__init__.py
plonetheme.onegov.egg-info/PKG-INFO
plonetheme.onegov.egg-info/SOURCES.txt
plonetheme.onegov.egg-info/dependency_links.txt
plonetheme.onegov.egg-info/entry_points.txt
plonetheme.onegov.egg-info/namespace_packages.txt
plonetheme.onegov.egg-info/not-zip-safe
plonetheme.onegov.egg-info/requires.txt
plonetheme.onegov.egg-info/top_level.txt
plonetheme/onegov/__init__.py
plonetheme/onegov/configure.zcml
plonetheme/onegov/customstyles.py
plonetheme/onegov/interfaces.py
plonetheme/onegov/lawgiver.zcml
plonetheme/onegov/meta.py
plonetheme/onegov/meta.zcml
plonetheme/onegov/permissions.zcml
plonetheme/onegov/registry.py
plonetheme/onegov/testing.py
plonetheme/onegov/utils.py
plonetheme/onegov/browser/__init__.py
plonetheme/onegov/browser/batching.py
plonetheme/onegov/browser/batchnavigation.pt
plonetheme/onegov/browser/configure.zcml
plonetheme/onegov/browser/customstyles.py
plonetheme/onegov/browser/customstyles_form.pt
plonetheme/onegov/browser/flyout.pt
plonetheme/onegov/browser/layout.py
plonetheme/onegov/browser/navigation.py
plonetheme/onegov/exportimport/__init__.py
plonetheme/onegov/exportimport/configure.zcml
plonetheme/onegov/exportimport/customstyles.py
plonetheme/onegov/locales/plonetheme.onegov-manual.pot
plonetheme/onegov/locales/plonetheme.onegov.pot
plonetheme/onegov/locales/de/LC_MESSAGES/plonetheme.onegov.po
plonetheme/onegov/locales/en/LC_MESSAGES/plonetheme.onegov.po
plonetheme/onegov/locales/es/LC_MESSAGES/plonetheme.onegov.po
plonetheme/onegov/locales/fr/LC_MESSAGES/plonetheme.onegov.po
plonetheme/onegov/locales/it/LC_MESSAGES/plonetheme.onegov.po
plonetheme/onegov/locales/no/LC_MESSAGES/plonetheme.onegov.po
plonetheme/onegov/patterns/__init__.py
plonetheme/onegov/patterns/configure.zcml
plonetheme/onegov/patterns/settings.py
plonetheme/onegov/portlets/__init__.py
plonetheme/onegov/portlets/configure.zcml
plonetheme/onegov/portlets/navigation.pt
plonetheme/onegov/portlets/navigation.py
plonetheme/onegov/portlets/static.pt
