Metadata-Version: 2.1
Name: plonetheme.onegov
Version: 4.0.3
Summary: Theme package for OneGov
Home-page: http://www.4teamwork.ch
Author: Julian Infanger
Author-email: julian.infanger@4teamwork.ch
License: GPL
Platform: UNKNOWN
Classifier: Framework :: Plone
Classifier: Programming Language :: Python
Provides-Extra: tests
